markdown_tool-0.1.3.data/scripts/markdown_tool.py
markdown_toolset/__init__.py
markdown_toolset/__version__.py
markdown_toolset/article_downloader.py
markdown_toolset/article_processor.py
markdown_toolset/image_downloader.py
markdown_toolset/out_path_maker.py
markdown_toolset/string_tools.py
markdown_toolset/www_tools.py
markdown_toolset/deduplicators/__init__.py
markdown_toolset/deduplicators/content_hash_dedup.py
markdown_toolset/deduplicators/deduplicator.py
markdown_toolset/deduplicators/name_hash_dedup.py
markdown_toolset/formatters/__init__.py
markdown_toolset/formatters/helpers.py
markdown_toolset/formatters/html.py
markdown_toolset/formatters/pdf.py
markdown_toolset/formatters/simple.py
markdown_toolset/transformers/__init__.py
markdown_toolset/transformers/html/__init__.py
markdown_toolset/transformers/html/transformer.py
markdown_toolset/transformers/md/__init__.py
markdown_toolset/transformers/md/transformer.py
tests/__init__.py
tests/test_article_downloader.py
tests/test_deduplicator.py
tests/test_image_downloader.py
tests/test_important_links.py
tests/test_markdown_transformer.py
tests/test_out_path_maker.py
tests/test_string_tools.py
tests/test_test.py
tests/test_www_tools.py
markdown_tool-0.1.3.dist-info/LICENSE.txt
markdown_tool-0.1.3.dist-info/METADATA
markdown_tool-0.1.3.dist-info/WHEEL
markdown_tool-0.1.3.dist-info/entry_points.txt
markdown_tool-0.1.3.dist-info/top_level.txt
markdown_tool-0.1.3.dist-info/RECORD
