Metadata-Version: 2.1
Name: markdown-tool
Version: 0.1.3
Summary: Markdown articles downloader and converter
Home-page: https://github.com/artiomn/markdown_articles_tool
Author: Artiom N.
Project-URL: Bug Tracker, https://github.com/artiomn/markdown_articles_tool/issues
Project-URL: Source Code, https://github.com/artiomn/markdown_articles_tool/
Keywords: html,markdown,pdf,downloader,images,markdown-parser,markdown-to-html,markdown converter,md,markdown-to-pdf,markdown-articles
Classifier: Development Status :: 3 - Alpha
Classifier: Intended Audience :: Developers
Classifier: Intended Audience :: Science/Research
Classifier: Intended Audience :: End Users/Desktop
Classifier: Intended Audience :: Other Audience
Classifier: Topic :: Text Processing :: Markup :: Markdown
Classifier: License :: OSI Approved :: MIT License
Classifier: Operating System :: OS Independent
Classifier: Programming Language :: Python :: 3
Classifier: Programming Language :: Python :: 3.8
Classifier: Programming Language :: Python :: 3.9
Classifier: Programming Language :: Python :: 3.10
Requires-Python: >=3.8
License-File: LICENSE.txt
Requires-Dist: markdown (==3.2.1)
Requires-Dist: pillow (==9.4.0)
Requires-Dist: requests (==2.23.0)
Requires-Dist: weasyprint (==51)
